irida_uploader_cl/__init__.py
irida_uploader_cl/irida_uploader_cl.py
irida_uploader_cl/api/__init__.py
irida_uploader_cl/api/api_calls.py
irida_uploader_cl/api/exceptions/__init__.py
irida_uploader_cl/api/exceptions/file_error.py
irida_uploader_cl/api/exceptions/irida_connection_error.py
irida_uploader_cl/api/exceptions/irida_key_error.py
irida_uploader_cl/api/exceptions/irida_resource_error.py
irida_uploader_cl/api/exceptions/irida_upload_canceled_exception.py
irida_uploader_cl/config/__init__.py
irida_uploader_cl/config/config.py
irida_uploader_cl/core/__init__.py
irida_uploader_cl/core/api_handler.py
irida_uploader_cl/core/cli_entry.py
irida_uploader_cl/core/exit_return.py
irida_uploader_cl/core/logger.py
irida_uploader_cl/core/model_validator.py
irida_uploader_cl/core/parsing_handler.py
irida_uploader_cl/messaging/__init__.py
irida_uploader_cl/messaging/pubsub.py
irida_uploader_cl/model/__init__.py
irida_uploader_cl/model/directory_status.py
irida_uploader_cl/model/project.py
irida_uploader_cl/model/sample.py
irida_uploader_cl/model/sequence_file.py
irida_uploader_cl/model/sequencing_run.py
irida_uploader_cl/model/validation_result.py
irida_uploader_cl/model/exceptions/__init__.py
irida_uploader_cl/model/exceptions/model_validation_error.py
irida_uploader_cl/parsers/__init__.py
irida_uploader_cl/parsers/parsers.py
irida_uploader_cl/parsers/directory/__init__.py
irida_uploader_cl/parsers/directory/parser.py
irida_uploader_cl/parsers/directory/sample_parser.py
irida_uploader_cl/parsers/directory/validation.py
irida_uploader_cl/parsers/exceptions/__init__.py
irida_uploader_cl/parsers/exceptions/directory_error.py
irida_uploader_cl/parsers/exceptions/sample_sheet_error.py
irida_uploader_cl/parsers/exceptions/sequence_file_error.py
irida_uploader_cl/parsers/exceptions/validation_error.py
irida_uploader_cl/parsers/miniseq/__init__.py
irida_uploader_cl/parsers/miniseq/parser.py
irida_uploader_cl/parsers/miniseq/sample_parser.py
irida_uploader_cl-0.2.dist-info/LICENSE
irida_uploader_cl-0.2.dist-info/METADATA
irida_uploader_cl-0.2.dist-info/WHEEL
irida_uploader_cl-0.2.dist-info/entry_points.txt
irida_uploader_cl-0.2.dist-info/top_level.txt
irida_uploader_cl-0.2.dist-info/RECORD
