Metadata-Version: 2.1
Name: irida-uploader-cl
Version: 0.2
Summary: IRIDA uploader: upload NGS data to IRIDA system
Home-page: https://github.com/duanjunhyq/irida_uploader_cl
Author: Jun Duan
Author-email: jun.duan@bccdc.ca
License: MIT
Keywords: IRIDA NGS uploader
Platform: UNKNOWN
Classifier: Programming Language :: Python :: 3
Classifier: License :: OSI Approved :: MIT License
Classifier: Operating System :: OS Independent
Requires-Python: >=3.5
Requires-Dist: rauth
Requires-Dist: autopep8
Requires-Dist: pycodestyle
Requires-Dist: requests
Requires-Dist: appdirs
Requires-Dist: pytest
Requires-Dist: mkdocs
Requires-Dist: cerberus
Requires-Dist: argparse
Requires-Dist: selenium
